Workbook
Name qtd_anos: APP!$D$21
Name patrimonio: APP!$D$23
Name aporte: APP!$D$20
Name rendimento_carteira: APP!$D$16
Name taxa_mensal: APP!$D$22
Name salario: APP!$D$15
Name sugestao_investimento: APP!$D$17

Sheet APP
B14: CONFIGURAÇÕES
B15: Salário | D15: 2000
B16: Rendimento Carteira | D16: 0.006
B17: Sugestão de Investimento (30%) | D17: =D15*30% -> 600
B19: INVESTIMENTO MENSAL
B20: Quanto investir por mês ? | D20: 200
B21: Por Quantos Anos ? | D21: 5
B22: Taxa de Rendimento mensal ? | D22: 0.01079
B23: Patrimônio acumulado ? | D23: =FV(taxa_mensal,qtd_anos*12,aporte*-1) -> 16755.383
B24: Dividendos Mensais ? | D24: =patrimonio*rendimento_carteira -> 100.5323
B26: Cenários | D26: Dividendo
A27: 2 | B27: Quanto em 2 Anos ? | C27: =FV($D$22,$A27*12,$D$20*-1) -> 5445.5255 | D27: =C27*rendimento_carteira -> 32.673153
A28: 5 | B28: Quanto em 5 Anos ? | C28: =FV($D$22,$A28*12,$D$20*-1) -> 16755.383 | D28: =C28*rendimento_carteira -> 100.5323
A29: 10 | B29: Quanto em 10 Anos ? | C29: =FV($D$22,$A29*12,$D$20*-1) -> 48656.843 | D29: =C29*rendimento_carteira -> 291.94106
A30: 20 | B30: Quanto em 20 Anos ? | C30: =FV($D$22,$A30*12,$D$20*-1) -> 225039.68 | D30: =C30*rendimento_carteira -> 1350.2381
A31: 30 | B31: Quanto em 30 Anos ? | C31: =FV($D$22,$A31*12,$D$20*-1) -> 864433.93 | D31: =C31*rendimento_carteira -> 5186.6036
B34: PERFIL | C34: Agressivo
B35: VALOR A SER INVESTIDO POR MÊS | C35: =aporte -> 200
B38: TIPO DE FII | C38: Percentual Sugerido | D38: Valores
B39: PAPEL | C39: =VLOOKUP($C$34&"-"&B39,apoio!$A:$D,4,FALSE) -> 0.5 | D39: =C39*$C$35 -> 100
B40: TIJOLO | C40: =VLOOKUP($C$34&"-"&B40,apoio!$A:$D,4,FALSE) -> 0.1 | D40: =C40*$C$35 -> 20
B41: HÍBRIDOS | C41: =VLOOKUP($C$34&"-"&B41,apoio!$A:$D,4,FALSE) -> 0.05 | D41: =C41*$C$35 -> 10
B42: FOFs | C42: =VLOOKUP($C$34&"-"&B42,apoio!$A:$D,4,FALSE) -> 0.05 | D42: =C42*$C$35 -> 10
B43: DESENVOLVIMENTO | C43: =VLOOKUP($C$34&"-"&B43,apoio!$A:$D,4,FALSE) -> 0.2 | D43: =C43*$C$35 -> 40
B44: HOTELARIAS | C44: =VLOOKUP($C$34&"-"&B44,apoio!$A:$D,4,FALSE) -> 0.1 | D44: =C44*$C$35 -> 20
D45: =SUM(D39:D44) -> 200
B63: PERFIL | C63: Conservador
B64: VALOR SUGERIDO POR MÊS | C64: =sugestao_investimento -> 600
B66: TIPO DE FII | C66: Percentual Sugerido | D66: Valores
B67: PAPEL | C67: =VLOOKUP($C$63&"-"&B67,apoio!$A:$D,4,FALSE) -> 0.3 | D67: =C67*$C$64 -> 180
B68: TIJOLO | C68: =VLOOKUP($C$63&"-"&B68,apoio!$A:$D,4,FALSE) -> 0.5 | D68: =C68*$C$64 -> 300
B69: HÍBRIDOS | C69: =VLOOKUP($C$63&"-"&B69,apoio!$A:$D,4,FALSE) -> 0.1 | D69: =C69*$C$64 -> 60
B70: FOFs | C70: =VLOOKUP($C$63&"-"&B70,apoio!$A:$D,4,FALSE) -> 0.1 | D70: =C70*$C$64 -> 60
B71: DESENVOLVIMENTO | C71: =VLOOKUP($C$63&"-"&B71,apoio!$A:$D,4,FALSE) -> 0 | D71: =C71*$C$64 -> 0
B72: HOTELARIAS | C72: =VLOOKUP($C$63&"-"&B72,apoio!$A:$D,4,FALSE) -> 0 | D72: =C72*$C$64 -> 0
D73: =SUM(D67:D72) -> 600

Sheet apoio
A2: CHAVE | B2: PERFIL | C2: TIPO DE FII | D2: %
A3: =B3&"-"&C3 -> Conservador-PAPEL | B3: Conservador | C3: PAPEL | D3: 0.3 | H3: %
A4: =B4&"-"&C4 -> Conservador-TIJOLO | B4: Conservador | C4: TIJOLO | D4: 0.5 | G4: Moderado-TIJOLO | H4: =VLOOKUP(G4,$A:$D,4,FALSE) -> 0.35
A5: =B5&"-"&C5 -> Conservador-HÍBRIDOS | B5: Conservador | C5: HÍBRIDOS | D5: 0.1
A6: =B6&"-"&C6 -> Conservador-FOFs | B6: Conservador | C6: FOFs | D6: 0.1
A7: =B7&"-"&C7 -> Conservador-DESENVOLVIMENTO | B7: Conservador | C7: DESENVOLVIMENTO | D7: 0
A8: =B8&"-"&C8 -> Conservador-HOTELARIAS | B8: Conservador | C8: HOTELARIAS | D8: 0
A9: =B9&"-"&C9 -> Moderado-PAPEL | B9: Moderado | C9: PAPEL | D9: 0.32
A10: =B10&"-"&C10 -> Moderado-TIJOLO | B10: Moderado | C10: TIJOLO | D10: 0.35
A11: =B11&"-"&C11 -> Moderado-HÍBRIDOS | B11: Moderado | C11: HÍBRIDOS | D11: 0.08
A12: =B12&"-"&C12 -> Moderado-FOFs | B12: Moderado | C12: FOFs | D12: 0.05
A13: =B13&"-"&C13 -> Moderado-DESENVOLVIMENTO | B13: Moderado | C13: DESENVOLVIMENTO | D13: 0.1
A14: =B14&"-"&C14 -> Moderado-HOTELARIAS | B14: Moderado | C14: HOTELARIAS | D14: 0.1
A15: =B15&"-"&C15 -> Agressivo-PAPEL | B15: Agressivo | C15: PAPEL | D15: 0.5
A16: =B16&"-"&C16 -> Agressivo-TIJOLO | B16: Agressivo | C16: TIJOLO | D16: 0.1
... A20: =B20&"-"&C20 -> Agressivo-HOTELARIAS | B20: Agressivo | C20: HOTELARIAS | D20: 0.1
